pytest_metadata/__init__.py
pytest_metadata/ci/__init__.py
pytest_metadata/ci/appveyor.py
pytest_metadata/ci/bitbucket.py
pytest_metadata/ci/circleci.py
pytest_metadata/ci/gitlab_ci.py
pytest_metadata/ci/jenkins.py
pytest_metadata/ci/taskcluster.py
pytest_metadata/ci/travis_ci.py
pytest_metadata/hooks.py
pytest_metadata/plugin.py
pytest_metadata-2.0.3.dist-info/entry_points.txt
pytest_metadata-2.0.3.dist-info/LICENSE
pytest_metadata-2.0.3.dist-info/WHEEL
pytest_metadata-2.0.3.dist-info/METADATA
pytest_metadata-2.0.3.dist-info/RECORD
