Metadata-Version: 2.1
Name: pytest-metadata
Version: 2.0.3
Summary: pytest plugin for test session metadata
Home-page: https://github.com/pytest-dev/pytest-metadata
License: MPL-2.0
Keywords: pytest,metadata
Author: Dave Hunt
Author-email: dhunt@mozilla.com
Requires-Python: >=3.7,<4.0
Classifier: Development Status :: 5 - Production/Stable
Classifier: Framework :: Pytest
Classifier: Intended Audience :: Developers
Classifier: License :: OSI Approved
Classifier: Operating System :: MacOS :: MacOS X
Classifier: Operating System :: Microsoft :: Windows
Classifier: Operating System :: POSIX
Classifier: Programming Language :: Python :: 3
Classifier: Programming Language :: Python :: 3.7
Classifier: Programming Language :: Python :: 3.8
Classifier: Programming Language :: Python :: 3.9
Classifier: Programming Language :: Python :: 3.10
Classifier: Programming Language :: Python :: 3.11
Classifier: Topic :: Software Development :: Quality Assurance
Classifier: Topic :: Software Development :: Testing
Classifier: Topic :: Utilities
Requires-Dist: pytest (>=3.0.0,<8.0.0)
Project-URL: Repository, https://github.com/pytest-dev/pytest-metadata
